aiohttp_openmetrics/__init__.py
aiohttp_openmetrics/py.typed
aiohttp_openmetrics-0.0.12.dist-info/AUTHORS
aiohttp_openmetrics-0.0.12.dist-info/METADATA
aiohttp_openmetrics-0.0.12.dist-info/WHEEL
aiohttp_openmetrics-0.0.12.dist-info/top_level.txt
aiohttp_openmetrics-0.0.12.dist-info/RECORD
