Metadata-Version: 2.1
Name: aiohttp-openmetrics
Version: 0.0.12
Summary: OpenMetrics provider for aiohttp
Author-email: Jelmer Vernooĳ <jelmer@jelmer.uk>
License: Apache v2 or later
Project-URL: Homepage, https://github.com/jelmer/aiohttp-openmetrics/
Project-URL: Repository, https://github.com/jelmer/aiohttp-openmetrics
Classifier: Development Status :: 4 - Beta
Classifier: Programming Language :: Python :: 3.6
Classifier: Programming Language :: Python :: 3.7
Classifier: Programming Language :: Python :: 3.8
Classifier: Programming Language :: Python :: 3.9
Classifier: Programming Language :: Python :: 3.10
Classifier: Programming Language :: Python :: Implementation :: CPython
Classifier: Programming Language :: Python :: Implementation :: PyPy
Classifier: Operating System :: POSIX
License-File: AUTHORS
Requires-Dist: aiohttp
Requires-Dist: prometheus-client
